layerlumos/__init__.py
layerlumos/layerlumos.py
layerlumos/materials.json
layerlumos/utils_materials.py
layerlumos/utils_spectra.py
layerlumos/materials/Ag_Yang.csv
layerlumos/materials/Al2O3_Querry.csv
layerlumos/materials/Al_Rakic.csv
layerlumos/materials/Cr_Rakic.csv
layerlumos/materials/Ni_Ordal.csv
layerlumos/materials/Pd_Werner.csv
layerlumos/materials/Si3N4_Kischkat.csv
layerlumos/materials/SiO2_Kischkat.csv
layerlumos/materials/TiN_Beliaev.csv
layerlumos/materials/TiO2_Siefke.csv
layerlumos/materials/Ti_Ordal.csv
layerlumos/materials/W_Ordal.csv
layerlumos-1.0.1.dist-info/LICENSE
layerlumos-1.0.1.dist-info/METADATA
layerlumos-1.0.1.dist-info/WHEEL
layerlumos-1.0.1.dist-info/top_level.txt
layerlumos-1.0.1.dist-info/RECORD
