Metadata-Version: 2.1
Name: layerlumos
Version: 1.0.1
Summary: An open-source software for TMM optical simulations
Author-email: Mingxuan Li <mil152@pitt.edu>
License: MIT
Project-URL: Homepage, https://github.com/mil152/layerlumos
Project-URL: Source, https://github.com/mil152/layerlumos
Classifier: Programming Language :: Python :: 3
Classifier: Intended Audience :: Science/Research
Classifier: License :: OSI Approved :: MIT License
Classifier: Operating System :: OS Independent
Classifier: Topic :: Scientific/Engineering
Requires-Python: >=3.8
License-File: LICENSE
Requires-Dist: numpy
Requires-Dist: scipy
Provides-Extra: dev
Requires-Dist: pytest ; extra == 'dev'
Requires-Dist: wheel ; extra == 'dev'
Requires-Dist: build ; extra == 'dev'
Requires-Dist: twine ; extra == 'dev'
Requires-Dist: sphinx ; extra == 'dev'
